{
    "$schema": "http://schema.management.azure.com/schemas/2014-04-01-preview/deploymentTemplate.json#",
    "contentVersion": "1.0.0.0",
    "parameters": {
    },
    "variables": {
        "location": "eastus"
    },
    "resources": [
        {
            "type": "Microsoft.Storage/storageAccounts",
            "name": "[parameters('storageName')]",
            "apiVersion": "2018-02-01",
            "location": "[variables('location')]",
            "sku": {
                "name": "Standard_LRS"
            }
        }
    ],
    "outputs": {
    }
}